{
  "dataset": "viajes",
  "source": "DTPM - Transantiago / RED Movilidad",
  "cut": "2025-04-27",
  "year": 2025,
  "month": 4,
  "separator": "|",
  "encoding": "utf-8",
  "columns": [
    "tipodia",
    "factor_expansion",
    "n_etapas",
    "tviaje",
    "distancia_eucl",
    "distancia_ruta",
    "tiempo_inicio_viaje",
    "tiempo_fin_viaje",
    "mediahora_inicio_viaje",
    "mediahora_fin_viaje",
    "periodo_inicio_viaje",
    "periodo_fin_viaje",
    "tipo_transporte_1",
    "tipo_transporte_2",
    "tipo_transporte_3",
    "tipo_transporte_4",
    "srv_1",
    "srv_2",
    "srv_3",
    "srv_4",
    "paradero_inicio_viaje",
    "paradero_fin_viaje",
    "comuna_inicio_viaje",
    "comuna_fin_viaje",
    "zona_inicio_viaje",
    "zona_fin_viaje",
    "modos",
    "tiempo_subida_1",
    "tiempo_subida_2",
    "tiempo_subida_3",
    "tiempo_subida_4",
    "tiempo_bajada_1",
    "tiempo_bajada_2",
    "tiempo_bajada_3",
    "tiempo_bajada_4",
    "zona_subida_1",
    "zona_subida_2",
    "zona_subida_3",
    "zona_subida_4",
    "zona_bajada_1",
    "zona_bajada_2",
    "zona_bajada_3",
    "zona_bajada_4",
    "paradero_subida_1",
    "paradero_subida_2",
    "paradero_subida_3",
    "paradero_subida_4",
    "paradero_bajada_1",
    "paradero_bajada_2",
    "paradero_bajada_3",
    "paradero_bajada_4",
    "mediahora_bajada_1",
    "mediahora_bajada_2",
    "mediahora_bajada_3",
    "mediahora_bajada_4",
    "periodo_bajada_1",
    "periodo_bajada_2",
    "periodo_bajada_3",
    "periodo_bajada_4",
    "id_tarjeta",
    "id_viaje",
    "netapassinbajada",
    "ultimaetapaconbajada",
    "contrato",
    "mediahora_inicio_viaje_hora",
    "mediahora_fin_viaje_hora",
    "op_1era_etapa",
    "op_2da_etapa",
    "op_3era_etapa",
    "op_4ta_etapa",
    "dt1",
    "dveh_ruta1",
    "dveh_euc1",
    "dt2",
    "dveh_ruta2",
    "dveh_euc2",
    "dt3",
    "dveh_ruta3",
    "dveh_euc3",
    "dveh_ruta4",
    "dveh_euc4",
    "dtfinal",
    "dveh_rutafinal",
    "dveh_eucfinal",
    "tipo_corte_etapa_viaje",
    "proposito",
    "entrada",
    "te0",
    "tv1",
    "tc1",
    "te1",
    "tv2",
    "tc2",
    "te2",
    "tv3",
    "tc3",
    "te3",
    "tv4",
    "egreso",
    "tviaje2",
    ""
  ],
  "column_count": 101,
  "row_count": 1129677,
  "file_size_bytes": 447146924,
  "source_file": "2025-04-27.viajes.csv",
  "extracted_at": "2026-02-27T14:07:20+00:00"
}